lambda_httpx/__init__.py
lambda_httpx/asynchronous.py
lambda_httpx/synchronous.py
lambda_httpx-0.2.dist-info/AUTHORS.rst
lambda_httpx-0.2.dist-info/LICENSE
lambda_httpx-0.2.dist-info/METADATA
lambda_httpx-0.2.dist-info/WHEEL
lambda_httpx-0.2.dist-info/top_level.txt
lambda_httpx-0.2.dist-info/RECORD
