Metadata-Version: 2.1
Name: lambda-httpx
Version: 0.2
Summary: Invoke AWS lambdas with httpx
Home-page: https://github.com/IlyaSukhanov/lambda-httpx
Author: Ilya Sukhanov
Author-email: ilya@sukhanov.net
License: MIT license
Keywords: aws,lambda-httpx
Classifier: Intended Audience :: Developers
Classifier: License :: OSI Approved :: MIT License
Classifier: Natural Language :: English
Classifier: Programming Language :: Python :: 3
Classifier: Programming Language :: Python :: 3.9
License-File: LICENSE
License-File: AUTHORS.rst
Requires-Dist: aioboto3
Requires-Dist: httpx
Requires-Dist: lambda-invoke
Provides-Extra: testing
Requires-Dist: pip ; extra == 'testing'
Requires-Dist: flake8 ; extra == 'testing'
Requires-Dist: tox ; extra == 'testing'
Requires-Dist: coverage ; extra == 'testing'
Requires-Dist: pytest ; extra == 'testing'
Requires-Dist: pyflakes ; extra == 'testing'
Requires-Dist: pytest-cov ; extra == 'testing'
Requires-Dist: bandit ; extra == 'testing'
Requires-Dist: black ; extra == 'testing'
Requires-Dist: isort ; extra == 'testing'
Requires-Dist: wheel ; extra == 'testing'
Requires-Dist: twine ; extra == 'testing'
Requires-Dist: build ; extra == 'testing'
Requires-Dist: with-time ; extra == 'testing'
